double_indent.py
double_indent_shiku-0.1.6.dist-info/METADATA
double_indent_shiku-0.1.6.dist-info/WHEEL
double_indent_shiku-0.1.6.dist-info/entry_points.txt
double_indent_shiku-0.1.6.dist-info/top_level.txt
double_indent_shiku-0.1.6.dist-info/RECORD
