Metadata-Version: 2.1
Name: double_indent_shiku
Version: 0.1.6
Summary: a code formatter indenting function and method definitions twice. Fork to indent function calls
Home-page: https://github.com/shiku-shi/double-indent
Author: Shiku Shi
Author-email: shiku-shi@users.noreply.github.com
License: MIT
Classifier: License :: OSI Approved :: MIT License
Classifier: Programming Language :: Python :: 3
Classifier: Programming Language :: Python :: 3 :: Only
Classifier: Programming Language :: Python :: Implementation :: CPython
Requires-Python: >=3.8
Requires-Dist: tokenize-rt
